exoctk/__init__.py
exoctk/helpers.py
exoctk/log_exoctk.py
exoctk/modelgrid.py
exoctk/references.py
exoctk/setup_package.py
exoctk/throughputs.py
exoctk/utils.py
exoctk/contam_visibility/__init__.py
exoctk/contam_visibility/astro_funcx.py
exoctk/contam_visibility/contamination_figure.py
exoctk/contam_visibility/ephemeris_old2x.py
exoctk/contam_visibility/f_visibilityPeriods.py
exoctk/contam_visibility/field_simulator.py
exoctk/contam_visibility/fig_explacation.pdf
exoctk/contam_visibility/make_contam_plot.py
exoctk/contam_visibility/make_contam_traces.py
exoctk/contam_visibility/math_extensionsx.py
exoctk/contam_visibility/miniTools.py
exoctk/contam_visibility/new_vis_plot.py
exoctk/contam_visibility/quaternionx.py
exoctk/contam_visibility/resolve.py
exoctk/contam_visibility/source_catalog.py
exoctk/contam_visibility/time_extensionsx.py
exoctk/contam_visibility/visibilityPA.py
exoctk/contam_visibility/vpa.py
exoctk/data/contam_visibility/.gitkeep
exoctk/data/contam_visibility/2MASS-2MASS.H.dat
exoctk/data/contam_visibility/2MASS-2MASS.J.dat
exoctk/data/contam_visibility/2MASS-2MASS.Ks.dat
exoctk/data/contam_visibility/JWST_elv4_20181031130000_ephem.txt
exoctk/data/contam_visibility/JWST_ephem_short.txt
exoctk/data/contam_visibility/lambda_order1-2.txt
exoctk/data/contam_visibility/predicted_gaia_colour.txt
exoctk/data/core/ModelGrid_tmp.fits
exoctk/data/core/bibtex.bib
exoctk/data/core/vega.txt
exoctk/data/core/modelgrid/ATLAS9_4000_40_m05.fits
exoctk/data/core/modelgrid/ATLAS9_4000_40_p00.fits
exoctk/data/core/modelgrid/ATLAS9_4000_45_m05.fits
exoctk/data/core/modelgrid/ATLAS9_4000_45_p00.fits
exoctk/data/core/modelgrid/ATLAS9_4250_40_m05.fits
exoctk/data/core/modelgrid/ATLAS9_4250_40_p00.fits
exoctk/data/core/modelgrid/ATLAS9_4250_45_m05.fits
exoctk/data/core/modelgrid/ATLAS9_4250_45_p00.fits
exoctk/data/exoctk_contam/.gitkeep
exoctk/data/exoctk_log/.gitkeep
exoctk/data/fortney/.gitkeep
exoctk/data/generic/.gitkeep
exoctk-1.2.6.dist-info/LICENSE.rst
exoctk-1.2.6.dist-info/METADATA
exoctk-1.2.6.dist-info/WHEEL
exoctk-1.2.6.dist-info/top_level.txt
exoctk-1.2.6.dist-info/RECORD
