Metadata-Version: 2.1
Name: exoctk
Version: 1.2.6
Summary: Exoplanet Characterization Toolkit
Author: Matthew Bourque, Néstor Espinoza, Joseph Filippazzo, Mees Fix, Teagan King, Catherine Martlin, Jennifer Medina, Natasha Batalha, Michael Fox, Jules Fowler, Jonathan Fraine, Matthew Hill, Nikole Lewis, Kevin Stevenson, Jeff Valenti, Hannah Wakeford
Project-URL: Repository, https://github.com/ExoCTK/exoctk
Keywords: astronomy,python
Classifier: Programming Language :: Python
License-File: LICENSE.rst
Requires-Dist: asteval
Requires-Dist: astropy
Requires-Dist: astroquery
Requires-Dist: bandit
Requires-Dist: batman-package
Requires-Dist: bibtexparser
Requires-Dist: bokeh<=3.2.1,>=3.0
Requires-Dist: boto3
Requires-Dist: corner
Requires-Dist: cython
Requires-Dist: docopt
Requires-Dist: docutils
Requires-Dist: flake8
Requires-Dist: flask
Requires-Dist: flask_wtf
Requires-Dist: gunicorn
Requires-Dist: h5py
Requires-Dist: hotsoss
Requires-Dist: ipython
Requires-Dist: matplotlib
Requires-Dist: numpy<2.0
Requires-Dist: numpydoc
Requires-Dist: pandas
Requires-Dist: paramiko
Requires-Dist: platon
Requires-Dist: pysiaf
Requires-Dist: pysynphot
Requires-Dist: pytest
Requires-Dist: pyyaml
Requires-Dist: pyvo
Requires-Dist: regions
Requires-Dist: scipy
Requires-Dist: scp
Requires-Dist: sphinx
Requires-Dist: sphinx_astropy
Requires-Dist: sqlalchemy
Requires-Dist: svo_filters
Requires-Dist: wtforms
Requires-Dist: werkzeug
Requires-Dist: jwst_gtvt
Provides-Extra: test
Requires-Dist: pytest; extra == "test"
Requires-Dist: pytest-cov; extra == "test"
Provides-Extra: docs
Requires-Dist: sphinx; extra == "docs"
Requires-Dist: sphinx_rtd_theme; extra == "docs"
Requires-Dist: stsci_rtd_theme; extra == "docs"
